dresscode/__init__.py
dresscode/__main__.py
dresscode/app.py
dresscode/constant.py
dresscode/page.py
dresscode/component/__init__.py
dresscode/component/button.py
dresscode/component/checkbutton.py
dresscode/component/dropdown_list.py
dresscode/component/editor.py
dresscode/component/entry.py
dresscode/component/image.py
dresscode/component/label.py
dresscode/component/path_entry.py
dresscode/component/radiobutton.py
dresscode/component/space.py
dresscode/component/spinbox.py
dresscode/component/table.py
dresscode/hooking/__init__.py
dresscode/hooking/ante_build_hook.py
dresscode/hooking/ante_release_hook.py
dresscode/hooking/post_build_hook.py
dresscode/hooking/post_release_hook.py
dresscode/pyrustic_data/build_report.json
dresscode/pyrustic_data/hooking.json
dresscode/pyrustic_data/hubstore.json
dresscode/pyrustic_data/release_info.json
dresscode/pyrustic_data/backstage/config/build.json
dresscode/pyrustic_data/backstage/config/init.json
dresscode/pyrustic_data/backstage/config/release.json
dresscode/pyrustic_data/backstage/data/github_release_form.json
dresscode/pyrustic_data/backstage/report/build_report.json
dresscode/pyrustic_data/backstage/report/release_report.json
dresscode/pyrustic_data/hubstore/img.json
dresscode/pyrustic_data/hubstore/promotion.json
secret/SCRATCH.py
secret/__init__.py
tests/__init__.py
dresscode-0.0.5.dist-info/LICENSE
dresscode-0.0.5.dist-info/METADATA
dresscode-0.0.5.dist-info/WHEEL
dresscode-0.0.5.dist-info/entry_points.txt
dresscode-0.0.5.dist-info/top_level.txt
dresscode-0.0.5.dist-info/RECORD
