Metadata-Version: 2.1
Name: dresscode
Version: 0.0.5
Summary: Dress up your code with a beautiful graphical user interface !
Home-page: https://github.com/pyrustic/dresscode
Author: Pyrustic Evangelist
Author-email: pyrustic@protonmail.com
Maintainer: Pyrustic Evangelist
Maintainer-email: pyrustic@protonmail.com
License: MIT
Keywords: gui,productivity,framework,python,pyrustic,tkinter,desktop-application,lightweight
Platform: UNKNOWN
Classifier: Programming Language :: Python :: 3
Classifier: License :: OSI Approved :: MIT License
Classifier: Operating System :: OS Independent
Requires-Python: >=3.5
Requires-Dist: pyrustic
